LICENSE
README.md
setup.py
hutk/__init__.py
hutk.egg-info/PKG-INFO
hutk.egg-info/SOURCES.txt
hutk.egg-info/dependency_links.txt
hutk.egg-info/top_level.txt