Metadata-Version: 2.1
Name: hutk
Version: 3.0
Summary: A module for new programers or allameh helli school
Author: M.P.Abdi
Author-email: m.p.abdi90@gmail.com
License: MIT
Classifier: Programming Language :: Python :: 3
Classifier: Operating System :: OS Independent
Requires-Python: >= 3.6
License-File: LICENSE
